<relaton-collection xmlns="https://open.ribose.com/relaton-xml"><title>OGC GeoZarr Specification</title><contributor><role type='author'/><organization><name>OGC</name></organization></contributor><relation type='partOf'><bibdata type="standard" schema-version="v1.2.9">
  <title type="main" language="en">OGC (add title text)</title>
  <uri type="xml">./documents/standard/template/geozarr-spec.xml</uri>
  <uri type="pdf">./documents/standard/template/geozarr-spec.pdf</uri>
  <uri type="doc">./documents/standard/template/geozarr-spec.doc</uri>
  <uri type="html">./documents/standard/template/geozarr-spec.html</uri>
  <uri type="rxl">./documents/standard/template/geozarr-spec.rxl</uri>
  <docidentifier type="ogc-external">http://www.opengis.net/doc/{doc-type}/{standard}/{m.n}</docidentifier>
  <docidentifier type="ogc-internal" primary="true">YY-999</docidentifier>
  <docnumber>YY-999</docnumber>
  <date type="published">
    <on>2029-03-30</on>
  </date>
  <date type="issued">
    <on>2029-03-30</on>
  </date>
  <date type="received">
    <on>2029-03-30</on>
  </date>
  <contributor>
    <role type="author"/>
    <organization>
      <name>Organization One</name>
    </organization>
  </contributor>
  <contributor>
    <role type="author"/>
    <organization>
      <name>Organization Two</name>
    </organization>
  </contributor>
  <contributor>
    <role type="editor"/>
    <person>
      <name>
        <completename>Christophe Noël</completename>
      </name>
    </person>
  </contributor>
  <contributor>
    <role type="editor"/>
    <person>
      <name>
        <completename>Brianna Pagán</completename>
      </name>
    </person>
  </contributor>
  <contributor>
    <role type="author">
      <description>committee</description>
    </role>
    <organization>
      <name>Open Geospatial Consortium</name>
      <subdivision>
technical
</subdivision>
      <abbreviation>OGC</abbreviation>
    </organization>
  </contributor>
  <contributor>
    <role type="publisher"/>
    <organization>
      <name>Open Geospatial Consortium</name>
      <abbreviation>OGC</abbreviation>
    </organization>
  </contributor>
  <edition>1.0</edition>
  <version>
    <draft>3.0</draft>
  </version>
  <language>en</language>
  <script>Latn</script>
  <abstract>&lt;p&gt;The GeoZarr Unified Data Model and Encoding Standard specifies a conceptual and implementation framework for representing multidimensional, geospatial datasets using the Zarr format. This Standard builds upon the Unidata Common Data Model (CDM) and the Climate and Forecast (CF) Conventions, and introduces interoperable constructs for tiling, georeferencing, and metadata integration.&lt;/p&gt;

&lt;p&gt;The model defines core elements—dimensions, coordinate variables, data variables, attributes—and optional extensions for multi-resolution overviews, affine geotransforms, and STAC metadata. Encoding guidance is provided for Zarr Version 2 and Zarr Version 3, including chunking, group hierarchy, and metadata conventions.&lt;/p&gt;

&lt;p&gt;GeoZarr aims to bridge scientific and geospatial communities by enabling round-trip transformations with formats such as NetCDF and GeoTIFF, and supporting compatibility with tools in the scientific Python and geospatial ecosystems. This Standard enables scalable, standards-compliant, and semantically rich data structures for cloud-native Earth observation applications.&lt;/p&gt;</abstract>
  <status>
    <stage>draft</stage>
  </status>
  <copyright>
    <from>2025</from>
    <owner>
      <organization>
        <name>Open Geospatial Consortium</name>
        <abbreviation>OGC</abbreviation>
      </organization>
    </owner>
  </copyright>
  <keyword>ogcdoc</keyword>
  <keyword>OGC document</keyword>
  <keyword>API</keyword>
  <keyword>openapi</keyword>
  <keyword>html</keyword>
  <ext>
    <doctype>standard</doctype>
    <subdoctype>implementation</subdoctype>
  </ext>
</bibdata></relation>
</relaton-collection>
